relic/chunky/core/__init__.py
relic/chunky/core/definitions.py
relic/chunky/core/errors.py
relic/chunky/core/filesystem.py
relic/chunky/core/protocols.py
relic/chunky/core/py.typed
relic/chunky/core/serialization.py
relic_tool_chunky_core-1.1.0.dist-info/LICENSE.txt
relic_tool_chunky_core-1.1.0.dist-info/METADATA
relic_tool_chunky_core-1.1.0.dist-info/WHEEL
relic_tool_chunky_core-1.1.0.dist-info/entry_points.txt
relic_tool_chunky_core-1.1.0.dist-info/top_level.txt
relic_tool_chunky_core-1.1.0.dist-info/RECORD
