Metadata-Version: 2.1
Name: relic-tool-chunky-core
Version: 1.1.0
Summary: Core files used to read/write Relic Chunky files.
Home-page: https://github.com/MAK-Relic-Tool/Relic-Tool-Chunky-Core
Author: Marcus Kertesz
Project-URL: Bug Tracker, https://github.com/MAK-Relic-Tool/Issue-Tracker/issues
Classifier: Programming Language :: Python :: 3 :: Only
Classifier: Programming Language :: Python :: 3.9
Classifier: Programming Language :: Python :: 3.10
Classifier: License :: OSI Approved :: GNU General Public License v3 (GPLv3)
Classifier: Operating System :: OS Independent
Requires-Python: >=3.9
License-File: LICENSE.txt
Requires-Dist: mak-serialization-tools (~=2022.0a19)
Requires-Dist: relic-tool-core (~=1.0.0)
Requires-Dist: fs
